ytmcp/__init__.py
ytmcp/__main__.py
ytmcp/cli.py
ytmcp/server.py
ytmcp/youtube_transcript_api/__init__.py
ytmcp/youtube_transcript_api/__main__.py
ytmcp/youtube_transcript_api/_api.py
ytmcp/youtube_transcript_api/_cli.py
ytmcp/youtube_transcript_api/_errors.py
ytmcp/youtube_transcript_api/_settings.py
ytmcp/youtube_transcript_api/_transcripts.py
ytmcp/youtube_transcript_api/formatters.py
ytmcp/youtube_transcript_api/proxies.py
ytmcp/youtube_transcript_api/py.typed
ytmcp-1.0.1.dist-info/licenses/LICENSE
ytmcp-1.0.1.dist-info/METADATA
ytmcp-1.0.1.dist-info/WHEEL
ytmcp-1.0.1.dist-info/entry_points.txt
ytmcp-1.0.1.dist-info/top_level.txt
ytmcp-1.0.1.dist-info/RECORD
