Metadata-Version: 2.4
Name: ytmcp
Version: 1.0.1
Summary: YouTube Transcript MCP Server - Fetch YouTube transcripts with timestamps via Model Context Protocol
Author-email: Shubham Shinde <shubhamshindesunil@gmail.com>
License: MIT
Project-URL: Homepage, https://github.com/shubhamshnd/ytmcp
Project-URL: Repository, https://github.com/shubhamshnd/ytmcp.git
Project-URL: Issues, https://github.com/shubhamshnd/ytmcp/issues
Project-URL: Documentation, https://github.com/shubhamshnd/ytmcp#readme
Keywords: youtube,transcript,mcp,ai,claude,subtitles,captions
Classifier: Development Status :: 4 - Beta
Classifier: Intended Audience :: Developers
Classifier: License :: OSI Approved :: MIT License
Classifier: Programming Language :: Python :: 3
Classifier: Programming Language :: Python :: 3.8
Classifier: Programming Language :: Python :: 3.9
Classifier: Programming Language :: Python :: 3.10
Classifier: Programming Language :: Python :: 3.11
Classifier: Programming Language :: Python :: 3.12
Classifier: Topic :: Software Development :: Libraries :: Python Modules
Classifier: Topic :: Internet :: WWW/HTTP
Classifier: Topic :: Multimedia :: Video
Requires-Python: >=3.8
License-File: LICENSE
Requires-Dist: requests>=2.25.0
Requires-Dist: defusedxml>=0.7.0
Provides-Extra: dev
Requires-Dist: pytest>=6.0; extra == "dev"
Requires-Dist: pytest-asyncio>=0.18.0; extra == "dev"
Requires-Dist: black>=22.0; extra == "dev"
Requires-Dist: flake8>=4.0; extra == "dev"
Requires-Dist: mypy>=0.950; extra == "dev"
Dynamic: license-file
